opc_full_connect/__init__.py
opc_full_connect/certificate_creation.py
opc_full_connect/opcua_access.py
opc_full_connect-0.1.0.dist-info/LICENSE
opc_full_connect-0.1.0.dist-info/METADATA
opc_full_connect-0.1.0.dist-info/NOTICE
opc_full_connect-0.1.0.dist-info/WHEEL
opc_full_connect-0.1.0.dist-info/top_level.txt
opc_full_connect-0.1.0.dist-info/RECORD
