Metadata-Version: 2.1
Name: opc_full_connect
Version: 0.1.0
Summary: A Python library for connecting to OPC UA servers with OpenSSL support.
Home-page: https://github.com/Zmeypp/opcua_access
Author: Zmeypp
Author-email: lmayel@gmail.com
License: MIT
Classifier: Programming Language :: Python :: 3
Classifier: License :: OSI Approved :: MIT License
Classifier: Operating System :: OS Independent
Classifier: Intended Audience :: Developers
Classifier: Topic :: Software Development :: Libraries :: Python Modules
Requires-Python: >=3.6
License-File: LICENSE
License-File: NOTICE
Requires-Dist: asyncua ==1.1.0
Requires-Dist: opcua ==0.98.13
